extto/__init__.py
extto/__version__.py
extto/core.py
extto-1.1.0.dist-info/METADATA
extto-1.1.0.dist-info/WHEEL
extto-1.1.0.dist-info/top_level.txt
extto-1.1.0.dist-info/RECORD
