Metadata-Version: 2.4
Name: extto
Version: 1.1.0
Summary: A package for extracting data from text files
Home-page: https://extto.kragskow.group
Author: Jon Kragskow
Author-email: jgck20@bath.ac.uk
Project-URL: Bug Tracker, https://gitlab.com/kragskow-group/extto/issues
Project-URL: Documentation, https://extto.kragskow.group
Classifier: Programming Language :: Python :: 3
Classifier: License :: OSI Approved :: GNU General Public License v3 (GPLv3)
Classifier: Operating System :: OS Independent
Requires-Python: >=3.10
Dynamic: author
Dynamic: author-email
Dynamic: classifier
Dynamic: description
Dynamic: description-content-type
Dynamic: home-page
Dynamic: project-url
Dynamic: requires-python
Dynamic: summary
